.gitignore
README.txt
setup.cfg
setup.py
test.ini.template
doc/.gitignore
doc/Makefile
doc/conf.py
doc/index.rst
doc/introduction.rst
doc/advanced/index.rst
doc/api/index.rst
doc/api/object.rst
doc/api/object_meta.rst
doc/basics/connections_sessions.rst
doc/basics/index.rst
doc/basics/objects.rst
doc/basics/what_here.rst
doc/basics/first_steps/index.rst
doc/basics/first_steps/sneak_peek.rst
doc/basics/first_steps/what_we_did.rst
doc/basics/first_steps/you_may_ask.rst
src/.gitignore
src/Elephantoplasty.egg-info/PKG-INFO
src/Elephantoplasty.egg-info/SOURCES.txt
src/Elephantoplasty.egg-info/dependency_links.txt
src/Elephantoplasty.egg-info/requires.txt
src/Elephantoplasty.egg-info/top_level.txt
src/eplasty/__init__.py
src/eplasty/column.py
src/eplasty/conditions.py
src/eplasty/ctx.py
src/eplasty/cursor.py
src/eplasty/lazy.py
src/eplasty/paging.py
src/eplasty/query.py
src/eplasty/result.py
src/eplasty/session.py
src/eplasty/util.py
src/eplasty/field/__init__.py
src/eplasty/field/adapter.py
src/eplasty/field/base.py
src/eplasty/field/blob.py
src/eplasty/field/file.py
src/eplasty/field/helper.py
src/eplasty/field/image.py
src/eplasty/field/one_column.py
src/eplasty/field/simple.py
src/eplasty/object/__init__.py
src/eplasty/object/base.py
src/eplasty/object/const.py
src/eplasty/object/exc.py
src/eplasty/object/meta.py
src/eplasty/object/tree.py
src/eplasty/relation/__init__.py
src/eplasty/relation/base.py
src/eplasty/relation/const.py
src/eplasty/relation/many_to_many.py
src/eplasty/relation/many_to_one.py
src/eplasty/relation/one_to_many.py
src/eplasty/relation/listlike/__init__.py
src/eplasty/relation/listlike/list_to_one.py
src/eplasty/relation/listlike/one_to_list.py
src/test/__init__.py
src/test/pythons.yotpeg
src/test/test_basic.py
src/test/test_conditions.py
src/test/test_ctx.py
src/test/test_dependent.py
src/test/test_eafp_relation.py
src/test/test_exc.py
src/test/test_file.py
src/test/test_identity.py
src/test/test_inheritance.py
src/test/test_many2many.py
src/test/test_many2many_self.py
src/test/test_many2one.py
src/test/test_one2list.py
src/test/test_one2many.py
src/test/test_query.py
src/test/test_table.py
src/test/test_threading.py
src/test/test_tree.py
