Metadata-Version: 1.1
Name: Elephantoplasty
Version: 0.1
Summary: A PostgreSQL ORM
Home-page: http://github.com/zefciu/Elephantoplasty
Author: Szymon Pyżalski
Author-email: zefciu <szymon@pythonista.net>
License: BSD
Keywords: orm postgresql psql pg persistence sql relational database
Platform: UNKNOWN
Classifier: Development Status :: 3 - Alpha
Classifier: Intended Audience :: Developers
Classifier: License :: OSI Approved :: BSD License
Classifier: Programming Language :: Python :: 3
Classifier: Programming Language :: Python :: 3.2
Classifier: Programming Language :: SQL
Classifier: Topic :: Database :: Front-Ends
